LICENSE
README.md
setup.py
deltadash/__init__.py
deltadash.egg-info/PKG-INFO
deltadash.egg-info/SOURCES.txt
deltadash.egg-info/dependency_links.txt
deltadash.egg-info/top_level.txt
deltadash/enums/__init__.py
deltadash/enums/event.py
deltadash/enums/note.py
deltadash/maps/__init__.py
deltadash/maps/difficulty.py
deltadash/maps/event.py
deltadash/maps/note.py
deltadash/parser/__init__.py
deltadash/parser/ini.py