Metadata-Version: 2.1
Name: deltadash
Version: 0.1.0
Summary: A simple parser library for the game DeltaDash.
Home-page: https://github.com/RealistikDash/deltadash.py
License: MIT
Project-URL: GitHub: repo, https://github.com/RealistikDash/deltadash.py
Project-URL: GitHub: issues, https://github.com/RealistikDash/deltadash.py/issues
Classifier: Programming Language :: Python :: 3
Classifier: Programming Language :: Python :: 3.10
Classifier: Programming Language :: Python :: 3.9
Classifier: Programming Language :: Python :: 3.8
Classifier: Programming Language :: Python :: 3.7
Classifier: Programming Language :: Python :: 3.6
Classifier: License :: OSI Approved :: MIT License
Classifier: Development Status :: 4 - Beta
Classifier: Topic :: Games/Entertainment
Requires-Python: >=3.6
License-File: LICENSE
